sqlpoop.py
sqlpoop-0.2.dist-info/METADATA
sqlpoop-0.2.dist-info/WHEEL
sqlpoop-0.2.dist-info/top_level.txt
sqlpoop-0.2.dist-info/RECORD
