Metadata-Version: 2.4
Name: sqlpoop
Version: 0.2
Summary: drop in replacement for sqlite for multi writing using tcp with serialized writes
Author: Stabosa87
Author-email: stab@stab.ing
Classifier: Programming Language :: Python :: 3
Classifier: Operating System :: OS Independent
Classifier: License :: OSI Approved :: MIT License
Requires-Python: >=3.6
Dynamic: author
Dynamic: author-email
Dynamic: classifier
Dynamic: description
Dynamic: description-content-type
Dynamic: requires-python
Dynamic: summary
